{
    "user": [
        {
            "id": 1,
            "name": "Ali",
            "age": "18",
            "phone": "09124598738",
            "password": "001384"
        }
    ],
    "categories": [
        {
            "id": "1",
            "name": "ابزار برقی",
            "product": [
                {
                    "id": 1,
                    "name": "دریل 2 دور چکشی 1300 وات دیوالت",
                    "price": 20500000,
                    "description": "  دارای گیربکس فلزی - کنترل سرعت الکترونیک - ضمانت 12 ماه ( شرکت ابزار سپه ) - دارای کیف حمل ",
                    "brand": "دیوالت  Dewalt",
                    "image": "https://abzarnovin.storage.c2.liara.space/id1.jpg"
                },
                {
                    "id": 2,
                    "name": "PLUS دریل گیربکسی توسن مدل 0081",
                    "price": 5398000,
                    "description": "دریل گیربکسی توسن مدل 0081D-PLUS دارای یک موتور 1050 وات همراه با گیربکس دوحالته است و از یک سه‌نظام آچارخور برای استفاده از انواع مته و خاصیت چکشی برای سوراخ کردن مصالح ساختمانی بهره می‌برد",
                    "brand": "توسن - Tosan",
                    "image": "https://abzarnovin.storage.c2.liara.space/id2.jpg"
                },
                {
                    "id": 3,
                    "name": "CT10067 دريل چکشي کرون مدل",
                    "price": 5092000,
                    "description": "دارای کلید گردان روی شستی اصلی برای تنظیم سرعت گردش مجهز به چرخ دنده‌های فلزی برای دوام بیشتر دستگاه دسته کمکی دارای استاندارد CE اروپا و GS آلمان دارای دسته کمکی امکان چرخش 360 درجه ای سیستم چرخ",
                    "brand": "کرون - Crown",
                    "image": "https://abzarnovin.storage.c2.liara.space/id3.jpg"
                }
            ]
        },
        {
            "id": 2,
            "name": "ابزار دستی ",
            "product": [
                {
                    "id": 4,
                    "name": "انبر خار باز کن سر کج وی بی دبلیو مدل 534020",
                    "price": 2168000,
                    "description": "محصولی مقاوم در برابر ضربه و فشار",
                    "brand": "VBW-وی بی دبلیو",
                    "image": "https://abzarnovin.storage.c2.liara.space/id4.jpg"
                },
                {
                    "id": 5,
                    "name": "انبر دست 7 اینچ 596210",
                    "price": 2168000,
                    "description": "محصولی مقاوم در برابر ضربه و فشار",
                    "brand": "VBW-وی بی دبلیو",
                    "image": "https://abzarnovin.storage.c2.liara.space/id5.jpg"
                },
                {
                    "id": 6,
                    "name": "انبر دم باریک6 اینچ کنزاکس",
                    "price": 529000,
                    "description": "محصولی مقاوم در برابر ضربه و فشار",
                    "brand": "کنزاکس - Kenzax",
                    "image": "https://abzarnovin.storage.c2.liara.space/id6.jpg"
                },
                {
                    "id": 7,
                    "name": "سیم چین الکترونیکی کنزاکس",
                    "price": 248000,
                    "description": "محصولی مقاوم در برابر ضربه و فشار",
                    "brand": "کنزاکس - Kenzax",
                    "image": "https://abzarnovin.storage.c2.liara.space/id7.jpg"
                }
            ]
        },
        {
            "id": 3,
            "name": "ابزار بادی ",
            "product": [
                {
                    "id": 8,
                    "name": "آچار بکس بادی 1/2 اینچ مایتی سون",
                    "price": "14850000",
                    "description": "قدرت بالا: به دلیل استفاده از هوای فشرده، گشتاور بالایی دارد و می‌تواند پیچ‌های سفت و محکم را به راحتی باز یا بسته کند",
                    "brand": "مایتی سون - mighty-seven",
                    "image": "https://abzarnovin.storage.c2.liara.space/id8.jpg"
                },
                {
                    "id": 9,
                    "name": "مهره پرچ کن بادی نیمه اتومات مایتی سون",
                    "price": "38600000",
                    "description": "قدرت بالا: به دلیل استفاده از هوای فشرده، گشتاور بالایی دارد و می‌تواند پیچ‌های سفت و محکم را به راحتی باز یا بسته کند",
                    "brand": "مایتی سون - mighty-seven",
                    "image": "https://abzarnovin.storage.c2.liara.space/id9.jpg"
                },
                {
                    "id": 10,
                    "name": "پیستوله بادی H827E رونیکس",
                    "price": "4248000",
                    "description": "قدرت بالا: به دلیل استفاده از هوای فشرده، گشتاور بالایی دارد و می‌تواند پیچ‌های سفت و محکم را به راحتی باز یا بسته کند",
                    "brand": "رونیکس - RONIX",
                    "image": "https://abzarnovin.storage.c2.liara.space/id10.jpg"
                },
                {
                    "id": 11,
                    "name": "آچار جغجغه بادی ",
                    "price": "7600000 ",
                    "description": "قدرت بالا: به دلیل استفاده از هوای فشرده، گشتاور بالایی دارد و می‌تواند پیچ‌های سفت و محکم را به راحتی باز یا بسته کند",
                    "brand": "رونیکس - RONIX",
                    "image": "https://abzarnovin.storage.c2.liara.space/id11.jpg"
                }
            ]
        },
        {
            "id": 4,
            "name": "ابزار بنزینی ",
            "product": [
                {
                    "id": 12,
                    "name": "چمن زن بنزینی خودران گیر بکسی رونیکس",
                    "price": "37782000 ",
                    "description": "دارای موتور تک سیلندر-4 زمانه-هوا خنک و دارای قدرت 3500 وات 6/5 اسب بخار",
                    "brand": "رونیکس - RONIX",
                    "image": "https://abzarnovin.storage.c2.liara.space/id12.jpg"
                },
                {
                    "id": 13,
                    "name": "AL-7150 اره زنجیری بنزینی آلاندو  ",
                    "price": "5198000",
                    "description": "دارای موتور 2500 وات و حجم موتور 58 سی سس",
                    "brand": "آلاندو-ALANDO",
                    "image": ""
                },
                {
                    "id": 14,
                    "name": "موتور برق بنزینی 1200 وات رونیکس ",
                    "price": "5198000",
                    "description": "دارای توان 1200 وات",
                    "brand": "رونیکس - RONIX ",
                    "image": "https://abzarnovin.storage.c2.liara.space/id14.png"
                }
            ]
        }
    ]
}